sqlengine-1.1.0.dist-info/METADATA
sqlengine-1.1.0.dist-info/WHEEL
sqlengine/__init__.py
sqlengine/sqlengine.py
sqlengine-1.1.0.dist-info/RECORD
