Metadata-Version: 2.1
Name: SQLEngine
Version: 1.1.0
Summary: A simple wrapper enabling quick SQLAlchemy Engine creation for various DBMS.
Author-Email: Kapparina <116474667+Kapparina@users.noreply.github.com>
License: MIT
Requires-Python: <3.13,>=3.12
Requires-Dist: sqlalchemy>=2.0.23
Requires-Dist: pyodbc>=5.0.1
